calculus_core/__init__.py
calculus_core/adapters/__init__.py
calculus_core/adapters/coefficients/__init__.py
calculus_core/adapters/coefficients/aoki_velloso.py
calculus_core/adapters/coefficients/decourt_quaresma.py
calculus_core/adapters/coefficients/teixeira.py
calculus_core/adapters/repository/__init__.py
calculus_core/bootstrap.py
calculus_core/domain/__init__.py
calculus_core/domain/calculation/__init__.py
calculus_core/domain/calculation/aoki_velloso.py
calculus_core/domain/calculation/base.py
calculus_core/domain/calculation/decourt_quaresma.py
calculus_core/domain/calculation/teixeira.py
calculus_core/domain/method_registry.py
calculus_core/domain/model.py
calculus_core/domain/pile_catalogs.py
calculus_core/domain/pile_types.py
calculus_core/domain/soil_investigation.py
calculus_core/domain/soil_types.py
calculus_core/domain/value_objects.py
calculus_core/entrypoints/__init__.py
calculus_core/entrypoints/cli.py
calculus_core/entrypoints/streamlit_app/__init__.py
calculus_core/entrypoints/streamlit_app/app.py
calculus_core/entrypoints/streamlit_app/constants.py
calculus_core/entrypoints/streamlit_app/pages/1_Dados_do_Solo.py
calculus_core/entrypoints/streamlit_app/pages/2_Calculo_Simples.py
calculus_core/entrypoints/streamlit_app/pages/3_Comparativo_Lote.py
calculus_core/service_layer/__init__.py
calculus_core/service_layer/services.py
calculus_core/utils/logging_config.py
calculus_core-0.5.1.dist-info/WHEEL
calculus_core-0.5.1.dist-info/entry_points.txt
calculus_core-0.5.1.dist-info/METADATA
calculus_core-0.5.1.dist-info/RECORD
