Metadata-Version: 2.3
Name: calculus-core
Version: 0.5.1
Summary: Foundation load capacity calculation engine using semi-empirical methods
Author: Kaio Silva
Author-email: Kaio Silva <98492492+kaiosilva-dataeng@users.noreply.github.com>
Classifier: Programming Language :: Python :: 3.10
Classifier: Programming Language :: Python :: 3.11
Classifier: Programming Language :: Python :: 3.12
Classifier: Programming Language :: Python :: 3.13
Classifier: Programming Language :: Python :: 3.14
Requires-Dist: streamlit>=1.46.0 ; extra == 'streamlit'
Requires-Dist: pandas>=2.3.0 ; extra == 'streamlit'
Requires-Dist: altair>=5.5.0 ; extra == 'streamlit'
Requires-Dist: matplotlib>=3.10.8 ; extra == 'streamlit'
Requires-Python: >=3.10
Provides-Extra: streamlit
